{
  "schema_version": "v2",
  "episode": 439,
  "date": "2024-05-27",
  "episode_archetype": {
    "primary": "market_commentary",
    "secondary": [
      "qa_heavy"
    ]
  },
  "segment_breakdown": {
    "market_pct": 50,
    "qa_pct": 25,
    "life_or_aside_pct": 20,
    "ads_pct": 5,
    "principles_pct": 0
  },
  "market_regime": {
    "phase_label": "AI 多頭輪動",
    "narrative": "^TWII 收 21803.7695、1日 1.11%、20日 8.37%、60日 15.64%；QQQ 收 452.9753、1日 0.95%、20日 6.25%、60日 4.45%；SOXX 收 235.4958、1日 1.98%、20日 9.99%、60日 9.86%。",
    "geopolitical_factors": [],
    "regime_tags": [
      "AI",
      "半導體",
      "成長股"
    ]
  },
  "topics": [
    "AI 投資",
    "美股",
    "台股",
    "聽眾 QA"
  ],
  "host_state": {
    "leverage_state": null,
    "disclosed_positions": [
      {
        "asset": "未具名部位或題材",
        "stance": "他提到自身持股、佈局或操作體感",
        "reasoning": "謝孟恭回顧 2024 年第一季投資成績：美股靠 AI 狂噴、台股科技股也不錯，但櫃買小鬼股經歷大回檔，迫使他反思操作方式。主要心得是停損越來越難做、小型股極度…"
      }
    ],
    "self_critique": [
      {
        "target": "近期操作或判斷",
        "assessment": "他用自身案例檢討交易流程與耐心。",
        "tone": "self_deprecating"
      }
    ],
    "personal_arc_markers": []
  },
  "investment_logic": [
    {
      "claim": "AI 題材投資要分辨誰真的接到訂單、誰只是被市場敘事帶動。",
      "trigger": "AI 題材快速上漲或供應鏈故事擴散",
      "is_conditional": false,
      "condition": null,
      "action_bias": "hold",
      "risk_control": "AI 題材投資要分辨誰真的接到訂單、誰只是被市場敘事帶動。",
      "risk_control_type": "none",
      "evidence": "EP439 2024-05-27 摘述：謝孟恭回顧 2024 年第一季投資成績：美股靠 AI 狂噴、台股科技股也不錯，但櫃買小鬼股經歷大回檔，迫使他反思操作方式。主要心得是停損越來越難做、小型股極度難出場（流動性爛）、看準的東西容易被洗掉。同時發現 AI 題材已被炒到極限、熱門標的漲幅超前，開始缺乏便宜買點。對後市持保留態度，寧願等崩盤再抄底，否則真的不知道還能買什麼。 回答聽眾提問。",
      "source_type": "host_framework",
      "confidence": "medium"
    },
    {
      "claim": "看錯時要停損，但策略也要配合自己的資訊優勢與個性調整。",
      "trigger": "交易結果與原先假設不符",
      "is_conditional": false,
      "condition": null,
      "action_bias": "stop-out",
      "risk_control": "看錯時要停損，但策略也要配合自己的資訊優勢與個性調整。",
      "risk_control_type": "stop-loss",
      "evidence": "EP439 2024-05-27 摘述：謝孟恭回顧 2024 年第一季投資成績：美股靠 AI 狂噴、台股科技股也不錯，但櫃買小鬼股經歷大回檔，迫使他反思操作方式。主要心得是停損越來越難做、小型股極度難出場（流動性爛）、看準的東西容易被洗掉。同時發現 AI 題材已被炒到極限、熱門標的漲幅超前，開始缺乏便宜買點。對後市持保留態度，寧願等崩盤再抄底，否則真的不知道還能買什麼。 回答聽眾提問。",
      "source_type": "host_framework",
      "confidence": "medium"
    },
    {
      "claim": "小型股部位要考慮成交量，出量時可分批送出，避免想賣時賣不掉。",
      "trigger": "持有低流動性小型股",
      "is_conditional": false,
      "condition": null,
      "action_bias": "scale-out",
      "risk_control": "小型股部位要考慮成交量，出量時可分批送出，避免想賣時賣不掉。",
      "risk_control_type": "liquidity",
      "evidence": "EP439 2024-05-27 摘述：謝孟恭回顧 2024 年第一季投資成績：美股靠 AI 狂噴、台股科技股也不錯，但櫃買小鬼股經歷大回檔，迫使他反思操作方式。主要心得是停損越來越難做、小型股極度難出場（流動性爛）、看準的東西容易被洗掉。同時發現 AI 題材已被炒到極限、熱門標的漲幅超前，開始缺乏便宜買點。對後市持保留態度，寧願等崩盤再抄底，否則真的不知道還能買什麼。 回答聽眾提問。",
      "source_type": "host_framework",
      "confidence": "medium"
    }
  ],
  "trade_observations": [
    {
      "asset_or_sector": "台股",
      "asset_symbol": "^TWII",
      "asset_type": "index",
      "view": {
        "short_term": "neutral",
        "medium_term": "bullish",
        "long_term": "unstated"
      },
      "primary_horizon": "medium-term",
      "reasoning": "謝孟恭回顧 2024 年第一季投資成績：美股靠 AI 狂噴、台股科技股也不錯，但櫃買小鬼股經歷大回檔，迫使他反思操作方式。主要心得是停損越來越難做、小型股極度難出場（流動性爛）、看準的東西容易被洗掉。同時發現 AI 題…",
      "industry_nodes": [],
      "catalyst_anchor": null,
      "consensus_level": "unclear",
      "market_alignment": "^TWII 收 21803.7695、1日 1.11%、20日 8.37%、60日 15.64%",
      "tone": "serious"
    },
    {
      "asset_or_sector": "美股",
      "asset_symbol": "^GSPC",
      "asset_type": "index",
      "view": {
        "short_term": "neutral",
        "medium_term": "bullish",
        "long_term": "unstated"
      },
      "primary_horizon": "medium-term",
      "reasoning": "謝孟恭回顧 2024 年第一季投資成績：美股靠 AI 狂噴、台股科技股也不錯，但櫃買小鬼股經歷大回檔，迫使他反思操作方式。主要心得是停損越來越難做、小型股極度難出場（流動性爛）、看準的東西容易被洗掉。同時發現 AI 題…",
      "industry_nodes": [],
      "catalyst_anchor": null,
      "consensus_level": "unclear",
      "market_alignment": "^TWII 收 21803.7695、1日 1.11%、20日 8.37%、60日 15.64%；QQQ 收 452.9753、1日 0.95%、20日 6.25%、60日 4.45%；SOXX 收 235.4958、1日 1.98%、20日 9.99%、60日 9.86%",
      "tone": "serious"
    },
    {
      "asset_or_sector": "AI 題材",
      "asset_symbol": null,
      "asset_type": "theme",
      "view": {
        "short_term": "neutral",
        "medium_term": "bullish",
        "long_term": "unstated"
      },
      "primary_horizon": "medium-term",
      "reasoning": "謝孟恭回顧 2024 年第一季投資成績：美股靠 AI 狂噴、台股科技股也不錯，但櫃買小鬼股經歷大回檔，迫使他反思操作方式。主要心得是停損越來越難做、小型股極度難出場（流動性爛）、看準的東西容易被洗掉。同時發現 AI 題…",
      "industry_nodes": [],
      "catalyst_anchor": null,
      "consensus_level": "unclear",
      "market_alignment": "^TWII 收 21803.7695、1日 1.11%、20日 8.37%、60日 15.64%；QQQ 收 452.9753、1日 0.95%、20日 6.25%、60日 4.45%；SOXX 收 235.4958、1日 1.98%、20日 9.99%、60日 9.86%",
      "tone": "serious"
    }
  ],
  "qa_views": [
    {
      "category": "investment_operation",
      "question_theme": "聽眾提問與操作取捨",
      "viewpoint": "謝孟恭回顧 2024 年第一季投資成績：美股靠 AI 狂噴、台股科技股也不錯，但櫃買小鬼股經歷大回檔，迫使他反思操作方式。主要心得是停損越來越難做、小型股極度難出場（流動性爛）、看準的東西容易被洗掉。同時發現 AI 題材已被炒到極限、熱門…",
      "principle": "回答問題時，他傾向把選擇放回個人條件、風險承受度與可執行性。",
      "tone": "實用",
      "evidence": "EP439 2024-05-27 摘述：謝孟恭回顧 2024 年第一季投資成績：美股靠 AI 狂噴、台股科技股也不錯，但櫃買小鬼股經歷大回檔，迫使他反思操作方式。主要心得是停損越來越難做、小型股極度難出場（流動性爛）、看準的東西容易被洗掉。同時發現 AI 題材已被炒到極限、熱門標的漲幅超前，開始缺乏便宜買點。對後市持保留態度，寧願等崩盤再抄底，否則真的不知道還能買什麼。 回答聽眾提問。",
      "asker_persona": null
    }
  ],
  "catalysts": [],
  "narrative_threads": [
    {
      "thread_id": "ai_supply_chain_2023_2024",
      "label": "AI 供應鏈多頭",
      "this_episode_role": "update",
      "prior_episode_refs": []
    }
  ],
  "view_changes": [],
  "principles": [
    {
      "principle": "進出場規則要在情緒來之前先設好。",
      "explanation": "謝孟恭回顧 2024 年第一季投資成績：美股靠 AI 狂噴、台股科技股也不錯，但櫃買小鬼股經歷大回檔，迫使他反思操作方式。主要心得是停損越來越難做、小型股極度難出場（流動性爛）、看準的東西容易被洗掉。同時發現 AI 題…",
      "category": "exit_discipline",
      "evidence": "EP439 2024-05-27 摘述：謝孟恭回顧 2024 年第一季投資成績：美股靠 AI 狂噴、台股科技股也不錯，但櫃買小鬼股經歷大回檔，迫使他反思操作方式。主要心得是停損越來越難做、小型股極度難出場（流動性爛）、看準的東西容易被洗掉。同時發現 AI 題材已被炒到極限、熱門標的漲幅超前，開始缺乏便宜買點。對後市持保留態度，寧願等崩盤再抄底，否則真的不知道還能買什麼。 回答聽眾提問。"
    }
  ],
  "mantras_or_catchphrases": [],
  "warnings": [],
  "references": [],
  "non_tradeable_insights": [
    {
      "insight": "科技產業需求呈現 AI 強、傳統消費電子仍需確認復甦的分化。",
      "domain": "tech_industry"
    }
  ],
  "open_questions": []
}
