{
  "schema_version": "v2",
  "episode": 474,
  "date": "2024-07-27",
  "episode_archetype": {
    "primary": "industry_supply_chain",
    "secondary": [
      "market_commentary"
    ]
  },
  "segment_breakdown": {
    "market_pct": 45,
    "qa_pct": 5,
    "life_or_aside_pct": 15,
    "ads_pct": 8,
    "principles_pct": 27
  },
  "market_regime": {
    "phase_label": "震盪整理",
    "narrative": "^TWII 收 22119.21、1日 -3.29%、20日 -3.77%、60日 +7.92%；2330.TW 收 898.72、1日 -5.62%、20日 -3.75%、60日 +16.68%；SOXX 收 226.71、1日 +2.15%、20日 -6.06%、60日 +7.32%；QQQ 收 458.67、1日 +1.03%、20日 -3.87%、60日 +9.21%；NVDA 收 113.01、1日 +0.69%、20日 -8.82%、60日 +30.86%；盤面處於震盪整理，主持人的討論聚焦於波動下的部位與題材判斷。",
    "geopolitical_factors": [],
    "regime_tags": [
      "震盪盤",
      "族群輪動",
      "觀望"
    ]
  },
  "topics": [
    "AI 產業",
    "特斯拉",
    "生活雜談",
    "颱風過後談投資心態與市場修正"
  ],
  "host_state": {
    "leverage_state": null,
    "disclosed_positions": [
      {
        "asset": "特斯拉",
        "stance": "他在本集以自身部位或觀察案例討論",
        "reasoning": "作為盤面檢討與部位調整脈絡"
      }
    ],
    "self_critique": [],
    "personal_arc_markers": []
  },
  "investment_logic": [
    {
      "claim": "長期投資要看產業位置與公司執行，不被短線價格完全牽動。",
      "trigger": "持有小型或產業轉型公司",
      "is_conditional": false,
      "condition": null,
      "action_bias": "hold",
      "risk_control": "用時間與基本面驗證，不用短線波動放大倉位",
      "risk_control_type": "time-bound",
      "evidence": "EP474 2024-07-27 摘述：特斯拉 FSD V12 進展顯著，電動車產業長期向上；",
      "source_type": "host_framework",
      "confidence": "medium"
    }
  ],
  "trade_observations": [
    {
      "asset_or_sector": "台股盤面",
      "asset_symbol": "^TWII",
      "asset_type": "index",
      "view": {
        "short_term": "conditional",
        "medium_term": "conditional",
        "long_term": "unstated"
      },
      "primary_horizon": "medium-term",
      "reasoning": "他以台股急跌、反彈或融資籌碼變化作為調整部位的背景。",
      "industry_nodes": [],
      "catalyst_anchor": null,
      "consensus_level": "unclear",
      "market_alignment": "^TWII 收 22119.21、1日 -3.29%、20日 -3.77%、60日 +7.92%",
      "tone": "serious"
    },
    {
      "asset_or_sector": "半導體與 AI 硬體",
      "asset_symbol": "SOXX",
      "asset_type": "sector",
      "view": {
        "short_term": "conditional",
        "medium_term": "neutral",
        "long_term": "bullish"
      },
      "primary_horizon": "medium-term",
      "reasoning": "他把 AI 硬體供應鏈視為主線，但提醒估值、需求與訂單節奏需要確認。",
      "industry_nodes": [
        "AI infrastructure"
      ],
      "catalyst_anchor": null,
      "consensus_level": "crowded",
      "market_alignment": "SOXX 收 226.71、1日 +2.15%、20日 -6.06%、60日 +7.32%",
      "tone": "serious"
    },
    {
      "asset_or_sector": "特斯拉",
      "asset_symbol": "TSLA",
      "asset_type": "stock",
      "view": {
        "short_term": "conditional",
        "medium_term": "neutral",
        "long_term": "unstated"
      },
      "primary_horizon": "medium-term",
      "reasoning": "他在本集以特斯拉作為產業或資產案例，重點是等待需求、估值與景氣位置互相印證。",
      "industry_nodes": [],
      "catalyst_anchor": null,
      "consensus_level": "unclear",
      "market_alignment": "^TWII 收 22119.21、1日 -3.29%、20日 -3.77%、60日 +7.92%；2330.TW 收 898.72、1日 -5.62%、20日 -3.75%、60日 +16.68%；TSM 收 158.25、1日 +1.04%、20日 -5.65%、60日 +18.28%；SOXX 收 226.71、1日 +2.15%、20日 -6.06%、60日 +7.32%；QQQ 收 458.67、1日 +1.03%、20日 -3.87%、60日 +9.21%；NVDA 收 113.01、1日 +0.69%、20日 -8.82%、60日 +30.86%",
      "tone": "serious"
    }
  ],
  "qa_views": [],
  "catalysts": [],
  "narrative_threads": [
    {
      "thread_id": "ai_infrastructure_2024_2025",
      "label": "AI 基礎建設與應用輪動",
      "this_episode_role": "update",
      "prior_episode_refs": []
    }
  ],
  "view_changes": [],
  "principles": [],
  "mantras_or_catchphrases": [],
  "warnings": [],
  "references": [],
  "non_tradeable_insights": [
    {
      "insight": "AI 時代的企業軟體價值可能來自客製化、資料整理與落地流程，而不只是模型本身。",
      "domain": "tech_industry"
    }
  ],
  "open_questions": []
}
