{
  "episode": 40,
  "episode_date": "2020-03-30",
  "title": "沒人可以完全取代香港",
  "baseline_market_context": {
    "^TWII": {
      "market_date": "2020-03-30",
      "close": 9629.4297,
      "ret_1d_pct": -0.72,
      "ret_5d_pct": 8.32,
      "ret_20d_pct": -13.8,
      "ret_60d_pct": -19.6
    },
    "^GSPC": {
      "market_date": "2020-03-30",
      "close": 2626.6499,
      "ret_1d_pct": 3.35,
      "ret_5d_pct": 17.4,
      "ret_20d_pct": -15.0,
      "ret_60d_pct": -19.37
    },
    "^IXIC": {
      "market_date": "2020-03-30",
      "close": 7774.1499,
      "ret_1d_pct": 3.62,
      "ret_5d_pct": 13.31,
      "ret_20d_pct": -13.16,
      "ret_60d_pct": -14.5
    },
    "^VIX": {
      "market_date": "2020-03-30",
      "close": 57.08,
      "ret_1d_pct": -12.91,
      "ret_5d_pct": -7.32,
      "ret_20d_pct": 70.8,
      "ret_60d_pct": 357.74
    },
    "^TNX": {
      "market_date": "2020-03-30",
      "close": 0.67,
      "ret_1d_pct": -10.55,
      "ret_5d_pct": -12.3,
      "ret_20d_pct": -38.42,
      "ret_60d_pct": -64.4
    },
    "TWD=X": {
      "market_date": "2020-03-30",
      "close": 30.03,
      "ret_1d_pct": -0.45,
      "ret_5d_pct": -0.62,
      "ret_20d_pct": 0.75,
      "ret_60d_pct": -0.06
    },
    "2330.TW": {
      "market_date": "2020-03-30",
      "close": 238.5252,
      "ret_1d_pct": -2.01,
      "ret_5d_pct": 4.9,
      "ret_20d_pct": -13.15,
      "ret_60d_pct": -18.65
    },
    "QQQ": {
      "market_date": "2020-03-30",
      "close": 185.467,
      "ret_1d_pct": 3.64,
      "ret_5d_pct": 12.66,
      "ret_20d_pct": -11.08,
      "ret_60d_pct": -10.97
    },
    "SOXX": {
      "market_date": "2020-03-30",
      "close": 66.3582,
      "ret_1d_pct": 3.48,
      "ret_5d_pct": 14.8,
      "ret_20d_pct": -12.48,
      "ret_60d_pct": -18.05
    },
    "TSM": {
      "market_date": "2020-03-30",
      "close": 43.1187,
      "ret_1d_pct": 1.94,
      "ret_5d_pct": 5.66,
      "ret_20d_pct": -13.77,
      "ret_60d_pct": -19.6
    },
    "NVDA": {
      "market_date": "2020-03-30",
      "close": 6.6138,
      "ret_1d_pct": 5.09,
      "ret_5d_pct": 24.87,
      "ret_20d_pct": -3.92,
      "ret_60d_pct": 10.77
    },
    "TSLA": {
      "market_date": "2020-03-30",
      "close": 33.4753,
      "ret_1d_pct": -2.38,
      "ret_5d_pct": 15.62,
      "ret_20d_pct": -32.47,
      "ret_60d_pct": 16.7
    },
    "BTC-USD": {
      "market_date": "2020-03-30",
      "close": 6429.8418,
      "ret_1d_pct": 8.57,
      "ret_5d_pct": -3.76,
      "ret_20d_pct": -18.71,
      "ret_60d_pct": -32.38
    }
  },
  "mentioned_assets": [
    {
      "asset_name": "聯電",
      "symbol": "2303.TW",
      "asset_type": "stock",
      "matched_aliases": [
        "半導體",
        "半導體族群",
        "晶圓代工"
      ],
      "sources": [
        "sector_basket:半導體供應鏈",
        "trade_observations.asset_or_sector"
      ],
      "market": {
        "market_date": "2020-03-30",
        "close": 10.0241,
        "ret_1d_pct": -0.36,
        "ret_5d_pct": 1.45,
        "ret_20d_pct": -8.52,
        "ret_60d_pct": -15.71
      },
      "pricing_status": "ok"
    },
    {
      "asset_name": "台積電",
      "symbol": "2330.TW",
      "asset_type": "stock",
      "matched_aliases": [
        "半導體",
        "半導體族群",
        "晶圓代工"
      ],
      "sources": [
        "sector_basket:半導體供應鏈",
        "trade_observations.asset_or_sector"
      ],
      "market": {
        "market_date": "2020-03-30",
        "close": 238.5252,
        "ret_1d_pct": -2.01,
        "ret_5d_pct": 4.9,
        "ret_20d_pct": -13.15,
        "ret_60d_pct": -18.65
      },
      "pricing_status": "ok"
    },
    {
      "asset_name": "瑞昱",
      "symbol": "2379.TW",
      "asset_type": "stock",
      "matched_aliases": [
        "半導體",
        "半導體族群",
        "晶圓代工"
      ],
      "sources": [
        "sector_basket:半導體供應鏈",
        "trade_observations.asset_or_sector"
      ],
      "market": {
        "market_date": "2020-03-30",
        "close": 150.1084,
        "ret_1d_pct": -1.0,
        "ret_5d_pct": 18.1,
        "ret_20d_pct": -11.56,
        "ret_60d_pct": -15.68
      },
      "pricing_status": "ok"
    },
    {
      "asset_name": "聯發科",
      "symbol": "2454.TW",
      "asset_type": "stock",
      "matched_aliases": [
        "半導體",
        "半導體族群",
        "晶圓代工"
      ],
      "sources": [
        "sector_basket:半導體供應鏈",
        "trade_observations.asset_or_sector"
      ],
      "market": {
        "market_date": "2020-03-30",
        "close": 234.3861,
        "ret_1d_pct": -1.03,
        "ret_5d_pct": 9.25,
        "ret_20d_pct": -7.3,
        "ret_60d_pct": -24.38
      },
      "pricing_status": "ok"
    },
    {
      "asset_name": "聯詠",
      "symbol": "3034.TW",
      "asset_type": "stock",
      "matched_aliases": [
        "半導體",
        "半導體族群",
        "晶圓代工"
      ],
      "sources": [
        "sector_basket:半導體供應鏈",
        "trade_observations.asset_or_sector"
      ],
      "market": {
        "market_date": "2020-03-30",
        "close": 110.0831,
        "ret_1d_pct": 0.87,
        "ret_5d_pct": 13.03,
        "ret_20d_pct": -12.15,
        "ret_60d_pct": -19.68
      },
      "pricing_status": "ok"
    },
    {
      "asset_name": "日月光投控",
      "symbol": "3711.TW",
      "asset_type": "stock",
      "matched_aliases": [
        "半導體",
        "半導體族群",
        "晶圓代工"
      ],
      "sources": [
        "sector_basket:半導體供應鏈",
        "trade_observations.asset_or_sector"
      ],
      "market": {
        "market_date": "2020-03-30",
        "close": 44.5155,
        "ret_1d_pct": -1.0,
        "ret_5d_pct": 16.08,
        "ret_20d_pct": -15.55,
        "ret_60d_pct": -30.19
      },
      "pricing_status": "ok"
    },
    {
      "asset_name": "Apple",
      "symbol": "AAPL",
      "asset_type": "stock",
      "matched_aliases": [
        "Apple"
      ],
      "sources": [
        "transcript"
      ],
      "market": {
        "market_date": "2020-03-30",
        "close": 61.512,
        "ret_1d_pct": 2.85,
        "ret_5d_pct": 13.57,
        "ret_20d_pct": -14.73,
        "ret_60d_pct": -14.96
      },
      "pricing_status": "ok"
    },
    {
      "asset_name": "Netflix",
      "symbol": "NFLX",
      "asset_type": "stock",
      "matched_aliases": [
        "Netflix"
      ],
      "sources": [
        "transcript"
      ],
      "market": {
        "market_date": "2020-03-30",
        "close": 37.096,
        "ret_1d_pct": 3.88,
        "ret_5d_pct": 2.97,
        "ret_20d_pct": -2.65,
        "ret_60d_pct": 12.48
      },
      "pricing_status": "ok"
    },
    {
      "asset_name": "iShares Semiconductor ETF",
      "symbol": "SOXX",
      "asset_type": "sector",
      "matched_aliases": [
        "半導體",
        "半導體族群",
        "晶圓代工"
      ],
      "sources": [
        "sector_basket:半導體供應鏈",
        "trade_observations.asset_or_sector",
        "trade_observations.asset_symbol"
      ],
      "market": {
        "market_date": "2020-03-30",
        "close": 66.3582,
        "ret_1d_pct": 3.48,
        "ret_5d_pct": 14.8,
        "ret_20d_pct": -12.48,
        "ret_60d_pct": -18.05
      },
      "pricing_status": "ok"
    },
    {
      "asset_name": "台積電 ADR",
      "symbol": "TSM",
      "asset_type": "stock",
      "matched_aliases": [
        "半導體",
        "半導體族群",
        "晶圓代工"
      ],
      "sources": [
        "sector_basket:半導體供應鏈",
        "trade_observations.asset_or_sector"
      ],
      "market": {
        "market_date": "2020-03-30",
        "close": 43.1187,
        "ret_1d_pct": 1.94,
        "ret_5d_pct": 5.66,
        "ret_20d_pct": -13.77,
        "ret_60d_pct": -19.6
      },
      "pricing_status": "ok"
    },
    {
      "asset_name": "標普 500",
      "symbol": "^GSPC",
      "asset_type": "index",
      "matched_aliases": [],
      "sources": [
        "trade_observations.asset_symbol"
      ],
      "market": {
        "market_date": "2020-03-30",
        "close": 2626.6499,
        "ret_1d_pct": 3.35,
        "ret_5d_pct": 17.4,
        "ret_20d_pct": -15.0,
        "ret_60d_pct": -19.37
      },
      "pricing_status": "ok"
    }
  ],
  "sector_basket_matches": [
    "半導體供應鏈"
  ],
  "unresolved_mentions": []
}
