{
  "episode": 409,
  "episode_date": "2023-12-13",
  "title": "🐪 聖誕節家庭時光與人生體悟",
  "baseline_market_context": {
    "^TWII": {
      "market_date": "2023-12-13",
      "close": 17468.9297,
      "ret_1d_pct": 0.1,
      "ret_5d_pct": 0.62,
      "ret_20d_pct": 1.99,
      "ret_60d_pct": 3.24
    },
    "^GSPC": {
      "market_date": "2023-12-13",
      "close": 4707.0898,
      "ret_1d_pct": 1.37,
      "ret_5d_pct": 3.47,
      "ret_20d_pct": 4.7,
      "ret_60d_pct": 5.92
    },
    "^IXIC": {
      "market_date": "2023-12-13",
      "close": 14733.96,
      "ret_1d_pct": 1.38,
      "ret_5d_pct": 4.15,
      "ret_20d_pct": 4.54,
      "ret_60d_pct": 7.72
    },
    "^VIX": {
      "market_date": "2023-12-13",
      "close": 12.19,
      "ret_1d_pct": 0.99,
      "ret_5d_pct": -6.01,
      "ret_20d_pct": -13.91,
      "ret_60d_pct": -13.61
    },
    "^TNX": {
      "market_date": "2023-12-13",
      "close": 4.033,
      "ret_1d_pct": -4.11,
      "ret_5d_pct": -2.14,
      "ret_20d_pct": -9.19,
      "ret_60d_pct": -7.61
    },
    "TWD=X": {
      "market_date": "2023-12-13",
      "close": 31.4731,
      "ret_1d_pct": 0.46,
      "ret_5d_pct": -0.14,
      "ret_20d_pct": -1.88,
      "ret_60d_pct": -1.59
    },
    "2330.TW": {
      "market_date": "2023-12-13",
      "close": 553.5585,
      "ret_1d_pct": -0.17,
      "ret_5d_pct": 1.23,
      "ret_20d_pct": -0.69,
      "ret_60d_pct": 3.41
    },
    "QQQ": {
      "market_date": "2023-12-13",
      "close": 397.8224,
      "ret_1d_pct": 1.27,
      "ret_5d_pct": 4.85,
      "ret_20d_pct": 4.78,
      "ret_60d_pct": 9.16
    },
    "SOXX": {
      "market_date": "2023-12-13",
      "close": 181.068,
      "ret_1d_pct": 1.54,
      "ret_5d_pct": 9.45,
      "ret_20d_pct": 8.63,
      "ret_60d_pct": 15.69
    },
    "TSM": {
      "market_date": "2023-12-13",
      "close": 98.6119,
      "ret_1d_pct": 0.51,
      "ret_5d_pct": 4.36,
      "ret_20d_pct": 3.25,
      "ret_60d_pct": 15.82
    },
    "NVDA": {
      "market_date": "2023-12-13",
      "close": 48.0586,
      "ret_1d_pct": 0.9,
      "ret_5d_pct": 5.68,
      "ret_20d_pct": -3.15,
      "ret_60d_pct": 10.51
    },
    "TSLA": {
      "market_date": "2023-12-13",
      "close": 239.29,
      "ret_1d_pct": 0.96,
      "ret_5d_pct": -0.03,
      "ret_20d_pct": 0.79,
      "ret_60d_pct": -10.21
    },
    "BTC-USD": {
      "market_date": "2023-12-13",
      "close": 42890.7422,
      "ret_1d_pct": 3.48,
      "ret_5d_pct": -2.89,
      "ret_20d_pct": 15.02,
      "ret_60d_pct": 59.67
    }
  },
  "mentioned_assets": [
    {
      "asset_name": "和大",
      "symbol": "1536.TW",
      "asset_type": "stock",
      "matched_aliases": [
        "車用"
      ],
      "sources": [
        "sector_basket:電動車供應鏈"
      ],
      "market": {
        "market_date": "2023-12-13",
        "close": 59.0759,
        "ret_1d_pct": -0.65,
        "ret_5d_pct": -4.23,
        "ret_20d_pct": -3.62,
        "ret_60d_pct": -6.71
      },
      "pricing_status": "ok"
    },
    {
      "asset_name": "聯電",
      "symbol": "2303.TW",
      "asset_type": "stock",
      "matched_aliases": [
        "半導體"
      ],
      "sources": [
        "sector_basket:半導體供應鏈",
        "trade_observations.asset_or_sector"
      ],
      "market": {
        "market_date": "2023-12-13",
        "close": 44.6694,
        "ret_1d_pct": 0.6,
        "ret_5d_pct": 2.66,
        "ret_20d_pct": 2.24,
        "ret_60d_pct": 5.46
      },
      "pricing_status": "ok"
    },
    {
      "asset_name": "台達電",
      "symbol": "2308.TW",
      "asset_type": "stock",
      "matched_aliases": [
        "車用"
      ],
      "sources": [
        "sector_basket:電動車供應鏈"
      ],
      "market": {
        "market_date": "2023-12-13",
        "close": 292.2659,
        "ret_1d_pct": 0.66,
        "ret_5d_pct": -2.26,
        "ret_20d_pct": -1.14,
        "ret_60d_pct": -10.88
      },
      "pricing_status": "ok"
    },
    {
      "asset_name": "鴻海",
      "symbol": "2317.TW",
      "asset_type": "stock",
      "matched_aliases": [
        "車用"
      ],
      "sources": [
        "sector_basket:電動車供應鏈"
      ],
      "market": {
        "market_date": "2023-12-13",
        "close": 95.0239,
        "ret_1d_pct": 0.0,
        "ret_5d_pct": 0.0,
        "ret_20d_pct": 0.5,
        "ret_60d_pct": -4.72
      },
      "pricing_status": "ok"
    },
    {
      "asset_name": "台積電",
      "symbol": "2330.TW",
      "asset_type": "stock",
      "matched_aliases": [
        "半導體",
        "台積電"
      ],
      "sources": [
        "sector_basket:半導體供應鏈",
        "trade_observations.asset_or_sector",
        "transcript"
      ],
      "market": {
        "market_date": "2023-12-13",
        "close": 553.5585,
        "ret_1d_pct": -0.17,
        "ret_5d_pct": 1.23,
        "ret_20d_pct": -0.69,
        "ret_60d_pct": 3.41
      },
      "pricing_status": "ok"
    },
    {
      "asset_name": "華邦電",
      "symbol": "2344.TW",
      "asset_type": "stock",
      "matched_aliases": [
        "DRAM",
        "NAND",
        "記憶體"
      ],
      "sources": [
        "sector_basket:記憶體",
        "trade_observations.asset_or_sector"
      ],
      "market": {
        "market_date": "2023-12-13",
        "close": 27.4065,
        "ret_1d_pct": 0.36,
        "ret_5d_pct": 1.29,
        "ret_20d_pct": -3.67,
        "ret_60d_pct": 2.36
      },
      "pricing_status": "ok"
    },
    {
      "asset_name": "智邦",
      "symbol": "2345.TW",
      "asset_type": "stock",
      "matched_aliases": [
        "智邦"
      ],
      "sources": [
        "transcript"
      ],
      "market": {
        "market_date": "2023-12-13",
        "close": 515.8071,
        "ret_1d_pct": 1.33,
        "ret_5d_pct": -0.19,
        "ret_20d_pct": -0.19,
        "ret_60d_pct": 5.96
      },
      "pricing_status": "ok"
    },
    {
      "asset_name": "瑞昱",
      "symbol": "2379.TW",
      "asset_type": "stock",
      "matched_aliases": [
        "半導體"
      ],
      "sources": [
        "sector_basket:半導體供應鏈",
        "trade_observations.asset_or_sector"
      ],
      "market": {
        "market_date": "2023-12-13",
        "close": 432.8101,
        "ret_1d_pct": 2.52,
        "ret_5d_pct": 3.77,
        "ret_20d_pct": 12.22,
        "ret_60d_pct": 12.62
      },
      "pricing_status": "ok"
    },
    {
      "asset_name": "南亞科",
      "symbol": "2408.TW",
      "asset_type": "stock",
      "matched_aliases": [
        "DRAM",
        "NAND",
        "記憶體"
      ],
      "sources": [
        "sector_basket:記憶體",
        "trade_observations.asset_or_sector"
      ],
      "market": {
        "market_date": "2023-12-13",
        "close": 73.7,
        "ret_1d_pct": 1.66,
        "ret_5d_pct": 2.36,
        "ret_20d_pct": 9.02,
        "ret_60d_pct": 1.8
      },
      "pricing_status": "ok"
    },
    {
      "asset_name": "聯發科",
      "symbol": "2454.TW",
      "asset_type": "stock",
      "matched_aliases": [
        "半導體",
        "發哥"
      ],
      "sources": [
        "sector_basket:半導體供應鏈",
        "trade_observations.asset_or_sector",
        "transcript"
      ],
      "market": {
        "market_date": "2023-12-13",
        "close": 857.7217,
        "ret_1d_pct": 1.7,
        "ret_5d_pct": 3.02,
        "ret_20d_pct": 5.18,
        "ret_60d_pct": 25.16
      },
      "pricing_status": "ok"
    },
    {
      "asset_name": "聯詠",
      "symbol": "3034.TW",
      "asset_type": "stock",
      "matched_aliases": [
        "半導體"
      ],
      "sources": [
        "sector_basket:半導體供應鏈",
        "trade_observations.asset_or_sector"
      ],
      "market": {
        "market_date": "2023-12-13",
        "close": 463.9369,
        "ret_1d_pct": 0.58,
        "ret_5d_pct": 1.17,
        "ret_20d_pct": 5.19,
        "ret_60d_pct": 11.42
      },
      "pricing_status": "ok"
    },
    {
      "asset_name": "日月光投控",
      "symbol": "3711.TW",
      "asset_type": "stock",
      "matched_aliases": [
        "半導體",
        "日月光"
      ],
      "sources": [
        "sector_basket:半導體供應鏈",
        "trade_observations.asset_or_sector",
        "transcript"
      ],
      "market": {
        "market_date": "2023-12-13",
        "close": 121.4005,
        "ret_1d_pct": 0.39,
        "ret_5d_pct": 0.78,
        "ret_20d_pct": 3.17,
        "ret_60d_pct": 12.07
      },
      "pricing_status": "ok"
    },
    {
      "asset_name": "群聯",
      "symbol": "8299.TWO",
      "asset_type": "stock",
      "matched_aliases": [
        "DRAM",
        "NAND",
        "記憶體"
      ],
      "sources": [
        "sector_basket:記憶體",
        "trade_observations.asset_or_sector"
      ],
      "market": {
        "market_date": "2023-12-13",
        "close": 499.1776,
        "ret_1d_pct": 3.25,
        "ret_5d_pct": 6.93,
        "ret_20d_pct": 12.62,
        "ret_60d_pct": 14.04
      },
      "pricing_status": "ok"
    },
    {
      "asset_name": "AMD",
      "symbol": "AMD",
      "asset_type": "stock",
      "matched_aliases": [
        "AMD"
      ],
      "sources": [
        "transcript"
      ],
      "market": {
        "market_date": "2023-12-13",
        "close": 138.19,
        "ret_1d_pct": 0.42,
        "ret_5d_pct": 18.29,
        "ret_20d_pct": 15.27,
        "ret_60d_pct": 36.0
      },
      "pricing_status": "ok"
    },
    {
      "asset_name": "Broadcom",
      "symbol": "AVGO",
      "asset_type": "stock",
      "matched_aliases": [
        "博通"
      ],
      "sources": [
        "transcript"
      ],
      "market": {
        "market_date": "2023-12-13",
        "close": 105.8481,
        "ret_1d_pct": 1.62,
        "ret_5d_pct": 20.59,
        "ret_20d_pct": 12.0,
        "ret_60d_pct": 29.02
      },
      "pricing_status": "ok"
    },
    {
      "asset_name": "Alphabet",
      "symbol": "GOOGL",
      "asset_type": "stock",
      "matched_aliases": [
        "Google"
      ],
      "sources": [
        "transcript"
      ],
      "market": {
        "market_date": "2023-12-13",
        "close": 131.4833,
        "ret_1d_pct": 0.04,
        "ret_5d_pct": 1.96,
        "ret_20d_pct": -0.79,
        "ret_60d_pct": -3.96
      },
      "pricing_status": "ok"
    },
    {
      "asset_name": "Meta",
      "symbol": "META",
      "asset_type": "stock",
      "matched_aliases": [
        "Facebook",
        "臉書"
      ],
      "sources": [
        "transcript"
      ],
      "market": {
        "market_date": "2023-12-13",
        "close": 332.1336,
        "ret_1d_pct": 0.16,
        "ret_5d_pct": 5.45,
        "ret_20d_pct": -0.47,
        "ret_60d_pct": 9.73
      },
      "pricing_status": "ok"
    },
    {
      "asset_name": "Microsoft",
      "symbol": "MSFT",
      "asset_type": "stock",
      "matched_aliases": [
        "微軟"
      ],
      "sources": [
        "transcript"
      ],
      "market": {
        "market_date": "2023-12-13",
        "close": 368.0302,
        "ret_1d_pct": -0.0,
        "ret_5d_pct": 1.51,
        "ret_20d_pct": 1.31,
        "ret_60d_pct": 14.14
      },
      "pricing_status": "ok"
    },
    {
      "asset_name": "Micron",
      "symbol": "MU",
      "asset_type": "stock",
      "matched_aliases": [
        "DRAM",
        "NAND",
        "記憶體"
      ],
      "sources": [
        "sector_basket:記憶體",
        "trade_observations.asset_or_sector"
      ],
      "market": {
        "market_date": "2023-12-13",
        "close": 79.052,
        "ret_1d_pct": 2.09,
        "ret_5d_pct": 9.11,
        "ret_20d_pct": 3.4,
        "ret_60d_pct": 13.03
      },
      "pricing_status": "ok"
    },
    {
      "asset_name": "Netflix",
      "symbol": "NFLX",
      "asset_type": "stock",
      "matched_aliases": [
        "Netflix"
      ],
      "sources": [
        "transcript"
      ],
      "market": {
        "market_date": "2023-12-13",
        "close": 47.998,
        "ret_1d_pct": 3.67,
        "ret_5d_pct": 7.44,
        "ret_20d_pct": 6.98,
        "ret_60d_pct": 21.15
      },
      "pricing_status": "ok"
    },
    {
      "asset_name": "NVIDIA",
      "symbol": "NVDA",
      "asset_type": "stock",
      "matched_aliases": [
        "輝達"
      ],
      "sources": [
        "trade_observations.asset_symbol",
        "transcript"
      ],
      "market": {
        "market_date": "2023-12-13",
        "close": 48.0586,
        "ret_1d_pct": 0.9,
        "ret_5d_pct": 5.68,
        "ret_20d_pct": -3.15,
        "ret_60d_pct": 10.51
      },
      "pricing_status": "ok"
    },
    {
      "asset_name": "iShares Semiconductor ETF",
      "symbol": "SOXX",
      "asset_type": "sector",
      "matched_aliases": [
        "半導體"
      ],
      "sources": [
        "sector_basket:半導體供應鏈",
        "trade_observations.asset_or_sector"
      ],
      "market": {
        "market_date": "2023-12-13",
        "close": 181.068,
        "ret_1d_pct": 1.54,
        "ret_5d_pct": 9.45,
        "ret_20d_pct": 8.63,
        "ret_60d_pct": 15.69
      },
      "pricing_status": "ok"
    },
    {
      "asset_name": "Tesla",
      "symbol": "TSLA",
      "asset_type": "stock",
      "matched_aliases": [
        "特斯拉",
        "車用"
      ],
      "sources": [
        "sector_basket:電動車供應鏈",
        "transcript"
      ],
      "market": {
        "market_date": "2023-12-13",
        "close": 239.29,
        "ret_1d_pct": 0.96,
        "ret_5d_pct": -0.03,
        "ret_20d_pct": 0.79,
        "ret_60d_pct": -10.21
      },
      "pricing_status": "ok"
    },
    {
      "asset_name": "台積電 ADR",
      "symbol": "TSM",
      "asset_type": "stock",
      "matched_aliases": [
        "半導體"
      ],
      "sources": [
        "sector_basket:半導體供應鏈",
        "trade_observations.asset_or_sector"
      ],
      "market": {
        "market_date": "2023-12-13",
        "close": 98.6119,
        "ret_1d_pct": 0.51,
        "ret_5d_pct": 4.36,
        "ret_20d_pct": 3.25,
        "ret_60d_pct": 15.82
      },
      "pricing_status": "ok"
    },
    {
      "asset_name": "標普 500",
      "symbol": "^GSPC",
      "asset_type": "index",
      "matched_aliases": [],
      "sources": [
        "trade_observations.asset_symbol"
      ],
      "market": {
        "market_date": "2023-12-13",
        "close": 4707.0898,
        "ret_1d_pct": 1.37,
        "ret_5d_pct": 3.47,
        "ret_20d_pct": 4.7,
        "ret_60d_pct": 5.92
      },
      "pricing_status": "ok"
    },
    {
      "asset_name": "台股加權指數",
      "symbol": "^TWII",
      "asset_type": "index",
      "matched_aliases": [
        "台股",
        "大盤"
      ],
      "sources": [
        "transcript"
      ],
      "market": {
        "market_date": "2023-12-13",
        "close": 17468.9297,
        "ret_1d_pct": 0.1,
        "ret_5d_pct": 0.62,
        "ret_20d_pct": 1.99,
        "ret_60d_pct": 3.24
      },
      "pricing_status": "ok"
    }
  ],
  "sector_basket_matches": [
    "半導體供應鏈",
    "記憶體",
    "電動車供應鏈"
  ],
  "unresolved_mentions": []
}
